nebari_plugin_mlflow_aws/__about__.py
nebari_plugin_mlflow_aws/__init__.py
nebari_plugin_mlflow_aws/terraform/main.tf
nebari_plugin_mlflow_aws/terraform/outputs.tf
nebari_plugin_mlflow_aws/terraform/variables.tf
nebari_plugin_mlflow_aws/terraform/versions.tf
nebari_plugin_mlflow_aws/terraform/modules/keycloak/main.tf
nebari_plugin_mlflow_aws/terraform/modules/keycloak/outputs.tf
nebari_plugin_mlflow_aws/terraform/modules/keycloak/variables.tf
nebari_plugin_mlflow_aws/terraform/modules/keycloak/versions.tf
nebari_plugin_mlflow_aws/terraform/modules/mlflow/main.tf
nebari_plugin_mlflow_aws/terraform/modules/mlflow/outputs.tf
nebari_plugin_mlflow_aws/terraform/modules/mlflow/variables.tf
nebari_plugin_mlflow_aws/terraform/modules/mlflow/chart/.helmignore
nebari_plugin_mlflow_aws/terraform/modules/mlflow/chart/Chart.yaml
nebari_plugin_mlflow_aws/terraform/modules/mlflow/chart/values.yaml
nebari_plugin_mlflow_aws/terraform/modules/mlflow/chart/templates/NOTES.txt
nebari_plugin_mlflow_aws/terraform/modules/mlflow/chart/templates/_helpers.tpl
nebari_plugin_mlflow_aws/terraform/modules/mlflow/chart/templates/deployment.yaml
nebari_plugin_mlflow_aws/terraform/modules/mlflow/chart/templates/hpa.yaml
nebari_plugin_mlflow_aws/terraform/modules/mlflow/chart/templates/ingress.yaml
nebari_plugin_mlflow_aws/terraform/modules/mlflow/chart/templates/postgres.yaml
nebari_plugin_mlflow_aws/terraform/modules/mlflow/chart/templates/service.yaml
nebari_plugin_mlflow_aws/terraform/modules/mlflow/chart/templates/serviceaccount.yaml
nebari_plugin_mlflow_aws/terraform/modules/mlflow/chart/templates/traefik.yaml
nebari_plugin_mlflow_aws/terraform/modules/mlflow/chart/templates/tests/test-connection.yaml
nebari_plugin_mlflow_aws-0.0.15.dist-info/METADATA
nebari_plugin_mlflow_aws-0.0.15.dist-info/WHEEL
nebari_plugin_mlflow_aws-0.0.15.dist-info/entry_points.txt
nebari_plugin_mlflow_aws-0.0.15.dist-info/licenses/LICENSE.md
nebari_plugin_mlflow_aws-0.0.15.dist-info/RECORD
