Metadata-Version: 2.3
Name: nebari-plugin-mlflow-aws
Version: 0.0.15
Summary: MetroStar - MLFlow Plugin for AWS Nebari Platform
Project-URL: Documentation, https://github.com/MetroStar/nebari-mlflow-aws#readme
Project-URL: Issues, https://github.com/MetroStar/nebari-mlflow-aws/issues
Project-URL: Source, https://github.com/MetroStar/nebari-mlflow-aws
Author-email: Scott Blair <sblair@metrostar.com>, Ken Foster <kfoster@metrostar.com>
License-Expression: Apache-2.0
License-File: LICENSE.md
Classifier: Development Status :: 4 - Beta
Classifier: Programming Language :: Python
Classifier: Programming Language :: Python :: 3.7
Classifier: Programming Language :: Python :: 3.8
Classifier: Programming Language :: Python :: 3.9
Classifier: Programming Language :: Python :: 3.10
Classifier: Programming Language :: Python :: 3.11
Classifier: Programming Language :: Python :: Implementation :: CPython
Classifier: Programming Language :: Python :: Implementation :: PyPy
Requires-Python: >=3.7
Requires-Dist: nebari
